{
    "Degree Name": "B.S. in Computer Science",
    "Rotal Required Credits": 120,
    "Requirements": [
        {
            "Requirement Name": "GENERAL EDUCATION REQUIREMENT",
            "Requirements": [
                {
                    "General Education Requirement Name": "Academic Foundations",
                    "Requirements": [
                        {
                            "Requirement Type": "Subject Requirement",
                            "Requirements": [
                                {
                                    "Requirement Name": "First Year Experience requirement",
                                    "Minimum Credits": 4,
                                    "Maximum Credits": 4
                                },
                                {
                                    "Requirement Name": "English Composition requirement",
                                    "Minimum Credits": 6,
                                    "Maximum Credits": 7
                                },
                                {
                                    "Requirement Name": "Interdisciplinary requirement",
                                    "Minimum Credits": 3,
                                    "Maximum Credits": 3
                                },
                                {
                                    "Requirement Name": "Diverse Communities requirement",
                                    "Minimum Credits": 3,
                                    "Maximum Credits": 3
                                }
                            ]
                        }
                    ]
                },
                {
                    "General Education Requirement Name": "Distributed Disciplinary Foundations",
                    "Requirements": [
                        {

                        }
                    ]
                }
            ]
        },
        {
            "Requirement Name": "ADDITIONAL BACCALAUREATE REQUIREMENTS",
            "Requirements": [
                {
                    "Additional Baccalaureate Requirement Name": "University Requirements",
                    "Requirements": [
                        {

                        }
                    ]
                },
                {
                    "Additional Baccalaureate Requirement Name": "Degree Requirements",
                    "Requirements": [
                        {

                        }
                    ]
                }
            ]
        },
        {
            "Requirement Name": "MAJOR REQUIREMENTS",
            "Requirements": [
                {
                    "Major Requirement Name": "University Requirements",
                    "Requirements": [
                        {

                        }
                    ]
                },
                {
                    "Major Requirement Name": "Degree Requirements",
                    "Requirements": [
                        {

                        }
                    ]
                }
            ]
        }
    ]
}
